Single Elevator/Elevator_controller.v
`timescale 1ns/1ns
module controller (
    input [TARGET_BIT:0] floor_req,
    input [TARGET_BIT:0] call_floor,
    input new_floor_button_pressed,
    input stop,
    input clk,
    input rst,
    input  upward,
    input  downward,
    output reg door_status,
    output reg moving_up,
    output reg moving_down
);

//============= TOTAL FLOORS ====================
    parameter   MAX = 7,
                COUNTER_BIT=4,
                TARGET_BIT=2;

//============= PARAMETER =======================
    parameter   IDLE = 2'b00, 
                GO_UP = 2'b01,
                GO_DOWN = 2'b10,
                OPEN_DOOR = 2'b11;
//=============== ELEVATORS ====================
    parameter   elevtr1 = 2'b00,
                elevtr2 = 2'b01,
                elevtr3 = 2'b01;

//============= REGISTERS ======================

    reg [MAX:0] call_request;   // outside
    reg [MAX:0] cabin_request;  // inside  // one bit per floor  -request[2]=1 means'someone requested 2nd floor'
    reg [1:0] current_state;    
    reg [1:0] next_state;       
    reg [TARGET_BIT:0] floor_count;      //[2,0]
    reg [TARGET_BIT:0] next_target;      //[2,0]
    reg [COUNTER_BIT:0] door_timing_counter;      // [4,0]
    reg has_request_above, has_request_below;       
    integer j;
    wire [MAX:0] request = call_request | cabin_request;

//      QUEUE FOR FLOOR REQUESTS

always @(posedge clk or posedge rst) begin
    if (rst) begin
        call_request  <= 8'd0;
        cabin_request <= 8'd0;
    end 
    else begin
        if (upward || downward) begin
            call_request[call_floor] <= 1'b1;
        end
        if (new_floor_button_pressed) begin
            cabin_request[floor_req] <= 1'b1;
        end
        if (current_state == OPEN_DOOR && timeout) begin
            cabin_request[floor_count] <= 1'b0;
            call_request[floor_count]  <= 1'b0;
        end
    end
end

//    MOVEMENT OF LIFT - UP/DOWN 

reg [TARGET_BIT:0]target;
reg found;
integer i;
always @(*) begin
        target = 0;
        found = 0;
        if (request[floor_count]) begin      // if user entered same floor on which lift is present.
            target = floor_count;
            found = 1;
        end
        else if (moving_up) begin
            for (i = floor_count+1 ; i <= MAX; i = i + 1) begin
                if (request[i] && !found) begin
                    target = i;
                    found = 1;
                end
            end
        end 
        else if(moving_down) begin
            for (i = floor_count-1; i >= 0; i = i - 1) begin
                if (request[i] && !found) begin
                    target = i;
                    found = 1;
                end
            end
        end
        else begin               // if lift is not moving in either of the direction
            for(i = 0; i<MAX+1 ; i=i+1)begin                    //boundation - good for single request,for multiple request it should look 
                if (request[i] && !found) begin             //for the nearest floor wrt current floor.
                    target=i;
                    found=1;
                end
            end
        end
    
end

always @(posedge clk or posedge rst) begin
    if(rst)
        next_target <= 0;
    else 
        next_target<=target;
end

//      STATE DECISION

    always @(*) begin
        next_state = current_state;

        case (current_state)

        IDLE: begin
            if (|request) begin
                if (next_target > floor_count)
                    next_state = GO_UP;
                else if (next_target < floor_count)
                    next_state = GO_DOWN;
                else
                    next_state = IDLE;
            end
        end
           
        GO_UP,GO_DOWN:begin
            if (stop || next_target==floor_count ) begin
                next_state=OPEN_DOOR;
            end
            else  begin
                next_state=current_state;
            end
        end   

        OPEN_DOOR : begin
            if (timeout) begin
                next_state=IDLE;
            end
        end
        default: next_state=IDLE;
        endcase
    end

always @(posedge clk or posedge rst) begin
    if (rst) begin
        moving_up <= 1;
        moving_down <=0;
    end 
    else begin

        has_request_above = 1'b0;
        has_request_below = 1'b0;
        // Check ABOVE
        for (j = floor_count + 1; j <= MAX; j = j + 1) begin
            if (request[j]) begin
                has_request_above = 1'b1;
            end
        end
        // Check BELOW
        for (j = 0; j < floor_count; j = j + 1) begin
            if (request[j]) begin
                has_request_below = 1'b1;
            end
        end
        // Direction decision (NO dependency on previous state)
        if (current_state==IDLE) begin
            if (has_request_above) begin
                moving_up <= 1;
                moving_down <= 0;
            end 
            else if (has_request_below) begin
                moving_down <= 1;
                moving_up <= 0;
            end
        end
        
        // else: no change
    end
end

//      STATE TRANSITIONS

    always @(posedge clk or posedge rst) begin
        if (rst) begin
            current_state <= IDLE;
        end
        else begin
            current_state <= next_state;
        end
    end

//      FLOOR TRANSITION

always @(posedge clk or posedge rst) begin
    if (rst)begin 
        floor_count <= 0;
    end
    else if (current_state == GO_UP) begin
        if (floor_count < next_target && floor_count < MAX)   //  protection
                floor_count <= floor_count + 1;
        end
    else if (current_state == GO_DOWN) begin
        if (floor_count > next_target && floor_count > 0)             //  protection
            floor_count <= floor_count - 1;
        end
end

//              COUNTER

always @(posedge clk or posedge rst) begin
    if (rst)begin
        door_timing_counter <= 0;
    end
    else if (current_state == OPEN_DOOR) begin
        if(door_timing_counter < 25)
            door_timing_counter <= door_timing_counter+1;
    end
    else
        door_timing_counter <= 0;
end

    wire timeout=(door_timing_counter==20);

//       OUTPUT LOGIC

    always @(posedge clk or posedge rst) begin
        if (rst) begin
            door_status <= 1'b0;
        end
        else if(current_state == OPEN_DOOR && !timeout)begin
            door_status <= 1'b1;
        end
        else begin
            door_status <= 1'b0; 
        end
        
    end

endmodule

// TESTBENCH

module controller_tb;

    // ------------------ Signals ------------------
    reg [2:0] floor_req;
    reg [2:0] call_floor;
    reg new_floor_button_pressed;
    reg stop;
    reg clk;
    reg rst;
    reg upward;
    reg downward;
    reg [2:0]t;

    wire door_status;
    wire moving_up;
    wire moving_down;

    parameter   MAX = 7,                
                COUNTER_BIT=4,
                TARGET_BIT=2;
             

    // Instantiate DUT 
    controller dut (
        .floor_req(floor_req),
        .call_floor(call_floor),
        .new_floor_button_pressed(new_floor_button_pressed),
        .stop(stop),
        .clk(clk),
        .rst(rst),
        .upward(upward),
        .downward(downward),
        .door_status(door_status),
        .moving_up(moving_up),
        .moving_down(moving_down)
    );

    // ------------------ Clock Generation ------------------
    initial clk = 0;
    always #5 clk = ~clk;   // 100 MHz clock (10ns period)

    // ------------------ Reset Task ------------------
    task reset_dut;
        begin
            rst = 1;
            floor_req = 0;
            call_floor = 0;
            upward = 0;
            downward = 0;
            new_floor_button_pressed = 0;
            stop = 0;

            repeat(5) @(posedge clk);
            rst = 0;
            repeat(5) @(posedge clk);
        end
    endtask

    // ------------------ External Call (Hall Button) ------------------
    task call_elvtr(input [TARGET_BIT:0] call, input is_up);
        begin
            @(posedge clk);
            call_floor = call;
            $display("CALLED FROM FLOOR = %d",call);
            if (is_up) begin
                upward   = 1;
                $display("Moving up");
            end
            else begin    
                downward = 1;
                $display("Moving down");
            end
            repeat(2) @(posedge clk);   // Hold the signal for a couple of cycles

            upward   = 0;
            downward = 0;
            // call_floor = 0;
        end
    endtask

    // ------------------ Inside Cabin Button ------------------
    task press_button_inside(input [TARGET_BIT:0] floor);
        begin
            if (floor > dut.MAX) begin
                $display("ERROR: Invalid floor %0d", floor);
                disable press_button_inside;
            end

            @(posedge clk);
            floor_req = floor;
            new_floor_button_pressed = 1;
            $display("BUTTON PRESSED FOR FLOOR = %d",floor);

            @(posedge clk);
            new_floor_button_pressed = 0;
            floor_req = 0;
        end
    endtask

    // ------------------ Emergency Stop ------------------
    task emergency_stop;
        begin
            @(posedge clk);
            stop = 1;
            @(posedge clk);
            stop = 0;
            $display("[%0t] Emergency STOP asserted and released", $time);
        end
    endtask


// === SINGLE LINE PRINT MONITOR (Add this) ===
reg [MAX:0] prev_floor = 0;
reg prev_door = 0;

always @(posedge clk) begin
    if (dut.floor_count != prev_floor || door_status != prev_door) begin
        $display("[%0t] Door Open - %0d | Floor: %0d", 
                 $time, door_status, dut.floor_count);
        prev_floor <= dut.floor_count;
        prev_door  <= door_status;
    end
end



 // ------------------ Main Test Sequence ------------------
integer floor;
integer call;

initial begin
    $dumpfile("controller.vcd");
    $dumpvars(0, controller_tb);
    reset_dut();
    // Test 1: Call from floor 3 (up), then inside buttons 4 and 7

    repeat(80) begin          
            // Randomly generate hall calls or cabin presses
            if ($random % 5 == 0) begin
                emergency_stop();
            end 
            else if ($random % 3 == 0) begin
                call = $urandom_range(0,MAX);
                call_elvtr(call, $random % 2);
            end
                
            else begin
                floor = $urandom_range(0,MAX);
                press_button_inside(floor);
            end


            // Small random delay between requests
            repeat($urandom_range(5, 25)) @(posedge clk);
        end


    repeat(100) @(posedge clk);   // extra safety time
    $finish;
end

endmodule

controller.vcd
$date
	Sun Apr 12 10:22:14 2026
$end
$version
	Icarus Verilog
$end
$timescale
	1ns
$end
$scope module controller_tb $end
$var wire 1 ! moving_up $end
$var wire 1 " moving_down $end
$var wire 1 # door_status $end
$var parameter 32 $ COUNTER_BIT $end
$var parameter 32 % MAX $end
$var parameter 32 & TARGET_BIT $end
$var reg 3 ' call_floor [2:0] $end
$var reg 1 ( clk $end
$var reg 1 ) downward $end
$var reg 3 * floor_req [2:0] $end
$var reg 1 + new_floor_button_pressed $end
$var reg 1 , prev_door $end
$var reg 8 - prev_floor [7:0] $end
$var reg 1 . rst $end
$var reg 1 / stop $end
$var reg 1 0 upward $end
$var integer 32 1 call [31:0] $end
$var integer 32 2 floor [31:0] $end
$scope module dut $end
$var wire 3 3 call_floor [2:0] $end
$var wire 1 ( clk $end
$var wire 1 ) downward $end
$var wire 3 4 floor_req [2:0] $end
$var wire 1 + new_floor_button_pressed $end
$var wire 8 5 request [7:0] $end
$var wire 1 . rst $end
$var wire 1 / stop $end
$var wire 1 0 upward $end
$var wire 1 6 timeout $end
$var parameter 32 7 COUNTER_BIT $end
$var parameter 2 8 GO_DOWN $end
$var parameter 2 9 GO_UP $end
$var parameter 2 : IDLE $end
$var parameter 32 ; MAX $end
$var parameter 2 < OPEN_DOOR $end
$var parameter 32 = TARGET_BIT $end
$var parameter 2 > elevtr1 $end
$var parameter 2 ? elevtr2 $end
$var parameter 2 @ elevtr3 $end
$var reg 8 A cabin_request [7:0] $end
$var reg 8 B call_request [7:0] $end
$var reg 2 C current_state [1:0] $end
$var reg 1 # door_status $end
$var reg 5 D door_timing_counter [4:0] $end
$var reg 3 E floor_count [2:0] $end
$var reg 1 F found $end
$var reg 1 G has_request_above $end
$var reg 1 H has_request_below $end
$var reg 1 " moving_down $end
$var reg 1 ! moving_up $end
$var reg 2 I next_state [1:0] $end
$var reg 3 J next_target [2:0] $end
$var reg 3 K target [2:0] $end
$var integer 32 L i [31:0] $end
$var integer 32 M j [31:0] $end
$upscope $end
$scope task call_elvtr $end
$var reg 3 N call [2:0] $end
$var reg 1 O is_up $end
$upscope $end
$scope task emergency_stop $end
$upscope $end
$scope task press_button_inside $end
$var reg 3 P floor [2:0] $end
$upscope $end
$scope task reset_dut $end
$upscope $end
$upscope $end
$enddefinitions $end
$comment Show the parameter values. $end
$dumpall
b1 @
b1 ?
b0 >
b10 =
b11 <
b111 ;
b0 :
b1 9
b10 8
b100 7
b10 &
b111 %
b100 $
$end
#0
$dumpvars
bx P
xO
bx N
bx M
b1000 L
b0 K
b0 J
b0 I
xH
xG
0F
b0 E
b0 D
b0 C
b0 B
b0 A
06
b0 5
b0 4
b0 3
bx 2
bx 1
00
0/
1.
b0 -
0,
0+
b0 *
0)
0(
b0 '
0#
0"
1!
$end
#5
1(
#10
0(
#15
1(
#20
0(
#25
1(
#30
0(
#35
1(
#40
0(
#45
b0 M
0H
0G
0.
1(
#50
0(
#55
b0 M
1(
#60
0(
#65
b0 M
1(
#70
0(
#75
b0 M
1(
#80
0(
#85
b0 M
1(
#90
0(
#95
b0 M
b100 P
b100 2
1(
#100
0(
#105
1F
b100 K
b1000 L
b10000 5
b10000 A
b0 M
1+
b100 *
b100 4
1(
#110
0(
#115
b1 I
b100 J
1G
b0 M
b0 *
b0 4
0+
1(
#120
0(
#125
b1 C
b0 M
1G
1(
#130
0(
#135
b1000 L
1F
b100 K
b1 E
b0 M
1G
1(
#140
0(
#145
b1000 L
1F
b100 K
b10 E
b1 -
b1 M
1G
1(
#150
0(
#155
b1000 L
1F
b100 K
b11 E
b10 -
b10 M
1G
1(
#160
0(
#165
b11 I
1F
b100 K
b100 E
b11 -
b11 M
1G
1(
#170
0(
#175
b11 C
b100 -
b100 M
0G
1(
#180
0(
#185
1#
b1 D
b100 M
1(
#190
0(
#195
b10 D
1,
b100 M
1(
#200
0(
#205
b11 D
b100 M
1(
#210
0(
#215
b100 D
b100 M
b0 P
b0 2
1(
#220
0(
#225
1F
b100 K
b10001 5
b101 D
b10001 A
b100 M
1+
1(
#230
0(
#235
b110 D
1H
b100 M
0+
1(
#240
0(
#245
b111 D
b100 M
1H
1(
#250
0(
#255
b1000 D
b100 M
1H
1(
#260
0(
#265
b1001 D
b100 M
1H
1(
#270
0(
#275
b1010 D
b100 M
1H
1(
#280
0(
#285
b1011 D
b100 M
1H
1(
#290
0(
#295
b1100 D
b100 M
1H
1(
#300
0(
#305
b1101 D
b100 M
1H
1(
#310
0(
#315
b1110 D
b100 M
1H
1(
#320
0(
#325
b1111 D
b100 M
1H
b100 P
b100 2
1(
#330
0(
#335
b10000 D
b100 M
1H
1+
b100 *
b100 4
1(
#340
0(
#345
b10001 D
b100 M
1H
b0 *
b0 4
0+
1(
#350
0(
#355
b10010 D
b100 M
1H
1(
#360
0(
#365
b10011 D
b100 M
1H
1(
#370
0(
#375
b0 I
16
b10100 D
b100 M
1H
1(
#380
0(
#385
b1000 L
0F
b0 K
b1 5
0#
06
b10101 D
b0 C
b1 A
b100 M
1H
1(
#390
0(
#395
b10 I
1F
b11111111111111111111111111111111 L
b0 J
0!
1"
b0 D
0,
b100 M
1H
1(
#400
0(
#405
b10 C
b100 M
1H
1(
#410
0(
#415
b11111111111111111111111111111111 L
1F
b11 E
b100 M
1H
1(
#420
0(
#425
b11111111111111111111111111111111 L
1F
b10 E
b11 -
b11 M
1H
1(
#430
0(
#435
b11111111111111111111111111111111 L
1F
b1 E
b10 -
b10 M
1H
1(
#440
0(
#445
b11 I
1F
b0 E
b1 -
b1 M
1H
1(
#450
0(
#455
b11 C
b0 -
b0 M
0H
1(
#460
0(
#465
1#
b1 D
b0 M
1(
#470
0(
#475
b10 D
1,
b0 M
1(
#480
0(
#485
b11 D
b0 M
1(
#490
0(
#495
b100 D
b0 M
1(
#500
0(
#505
b101 D
b0 M
1(
#510
0(
#515
b110 D
b0 M
1(
#520
0(
#525
b111 D
b0 M
1(
#530
0(
#535
b1000 D
b0 M
1(
#540
0(
#545
b1001 D
b0 M
1(
#550
0(
#555
b1010 D
b0 M
1O
b1 N
b1 1
1(
#560
0(
#565
1F
b11 5
b1011 D
b10 B
b0 M
10
b1 '
b1 3
1(
#570
0(
#575
b1100 D
1G
b0 M
1(
#580
0(
#585
b1101 D
b0 M
1G
00
1(
#590
0(
#595
b1110 D
b0 M
1G
1(
#600
0(
#605
b1111 D
b0 M
1G
1(
#610
0(
#615
b10000 D
b0 M
1G
1(
#620
0(
#625
b10001 D
b0 M
1G
1(
#630
0(
#635
b10010 D
b0 M
1G
b100 N
b100 1
1(
#640
0(
#645
1F
b10011 5
b10011 D
b10010 B
b0 M
1G
10
b100 '
b100 3
1(
#650
0(
#655
b0 I
16
b10100 D
b0 M
1G
1(
#660
0(
#665
0F
b10010 5
0#
06
b10101 D
b0 C
b0 A
b0 M
1G
00
1(
#670
0(
#675
1F
b1 K
b1000 L
0"
1!
b0 D
0,
b0 M
1G
1(
#680
0(
#685
b1 I
b1 J
b0 M
1G
1(
#690
0(
#695
b1 C
b0 M
1G
1(
#700
0(
#705
b11 I
1F
b1 K
b1 E
b0 M
1G
1(
#710
0(
#715
b11 C
b1 -
b1 M
1G
1(
#720
0(
#725
1#
b1 D
b1 M
1G
1(
#730
0(
#735
b10 D
1,
b1 M
1G
1(
#740
0(
#745
b11 D
b1 M
1G
1(
#750
0(
#755
b100 D
b1 M
1G
1(
#760
0(
#765
b101 D
b1 M
1G
1(
#770
0(
#775
b110 D
b1 M
1G
1(
#780
0(
#785
b111 D
b1 M
1G
1(
#790
0(
#795
b1000 D
b1 M
1G
1(
#800
0(
#805
b1001 D
b1 M
1G
1(
#810
0(
#815
b1010 D
b1 M
1G
1(
#820
0(
#825
b1011 D
b1 M
1G
b101 P
b101 2
1(
#830
0(
#835
1F
b1 K
b110010 5
b100000 A
b1100 D
b1 M
1G
1+
b101 *
b101 4
1(
#840
0(
#845
b1101 D
b1 M
1G
b0 *
b0 4
0+
1(
#850
0(
#855
b1110 D
b1 M
1G
1(
#860
0(
#865
b1111 D
b1 M
1G
1(
#870
0(
#875
b10000 D
b1 M
1G
1(
#880
0(
#885
b10001 D
b1 M
1G
1(
#890
0(
#895
b10010 D
b1 M
1G
1(
#900
0(
#905
b10011 D
b1 M
1G
1(
#910
0(
#915
b0 I
16
b10100 D
b1 M
1G
1(
#920
0(
#925
b1000 L
1F
b100 K
b110000 5
0#
06
b10101 D
b0 C
b10000 B
b1 M
1G
1(
#930
0(
#935
b1 I
b100 J
b0 D
0,
b1 M
1G
1(
#940
0(
#945
b1 C
b1 M
1G
1(
#950
0(
#955
b1000 L
1F
b100 K
b10 E
b1 M
1G
1(
#960
0(
#965
b1000 L
1F
b100 K
b11 E
b10 -
b10 M
1G
1(
#970
0(
#975
b11 I
1F
b100 K
b100 E
b11 -
b11 M
1G
1(
#980
0(
#985
b11 C
b100 -
b100 M
1G
1(
#990
0(
#995
b1 D
1#
b100 M
1G
1(
#1000
0(
#1005
b10 D
1,
b100 M
1G
1(
#1010
0(
#1015
b11 D
b100 M
1G
1(
#1020
0(
#1025
b100 D
b100 M
1G
b111 P
b111 2
1(
#1030
0(
#1035
1F
b100 K
b10110000 5
b10100000 A
b101 D
b100 M
1G
1+
b111 *
b111 4
1(
#1040
0(
#1045
b110 D
b100 M
1G
b0 *
b0 4
0+
1(
#1050
0(
#1055
b111 D
b100 M
1G
1(
#1060
0(
#1065
b1000 D
b100 M
1G
1(
#1070
0(
#1075
b1001 D
b100 M
1G
1(
#1080
0(
#1085
b1010 D
b100 M
1G
1(
#1090
0(
#1095
b1011 D
b100 M
1G
1(
#1100
0(
#1105
b1100 D
b100 M
1G
1(
#1110
0(
#1115
b1101 D
b100 M
1G
1(
#1120
0(
#1125
b1110 D
b100 M
1G
1(
#1130
0(
#1135
b1111 D
b100 M
1G
1(
#1140
0(
#1145
b10000 D
b100 M
1G
1(
#1150
0(
#1155
b10001 D
b100 M
1G
1(
#1160
0(
#1165
b10010 D
b100 M
1G
1(
#1170
0(
#1175
b10011 D
b100 M
1G
1(
#1180
0(
#1185
b0 I
16
b10100 D
b100 M
1G
1(
#1190
0(
#1195
b1000 L
1F
b101 K
b10100000 5
b0 B
b0 C
06
b10101 D
0#
b100 M
1G
1(
#1200
0(
#1205
b1 I
b0 D
b101 J
0,
b100 M
1G
1(
#1210
0(
#1215
b1 C
b100 M
1G
1(
#1220
0(
#1225
b11 I
1F
b101 K
b101 E
b100 M
1G
1(
#1230
0(
#1235
b11 C
b101 -
b101 M
1G
1(
#1240
0(
#1245
1#
b1 D
b101 M
1G
1(
#1250
0(
#1255
b10 D
1,
b101 M
1G
1(
#1260
0(
#1265
b11 D
b101 M
1G
1+
b111 *
b111 4
1(
#1270
0(
#1275
b100 D
b101 M
1G
b0 *
b0 4
0+
1(
#1280
0(
#1285
b101 D
b101 M
1G
1(
#1290
0(
#1295
b110 D
b101 M
1G
1(
#1300
0(
#1305
b111 D
b101 M
1G
1(
#1310
0(
#1315
b1000 D
b101 M
1G
1(
#1320
0(
#1325
b1001 D
b101 M
1G
1(
#1330
0(
#1335
b1010 D
b101 M
1G
1(
#1340
0(
#1345
b1011 D
b101 M
1G
1(
#1350
0(
#1355
b1100 D
b101 M
1G
1(
#1360
0(
#1365
b1101 D
b101 M
1G
1(
#1370
0(
#1375
b1110 D
b101 M
1G
1(
#1380
0(
#1385
b1111 D
b101 M
1G
1(
#1390
0(
#1395
b10000 D
b101 M
1G
1(
#1400
0(
#1405
b10001 D
b101 M
1G
1(
#1410
0(
#1415
b10010 D
b101 M
1G
1/
1(
#1420
0(
#1425
b10011 D
b101 M
1G
0/
1(
#1430
0(
#1435
b0 I
16
b10100 D
b101 M
1G
1(
#1440
0(
#1445
b1000 L
1F
b111 K
b10000000 5
0#
06
b10101 D
b0 C
b10000000 A
b101 M
1G
1(
#1450
0(
#1455
b1 I
b111 J
b0 D
0,
b101 M
1G
1(
#1460
0(
#1465
b1 C
b101 M
1G
1(
#1470
0(
#1475
b1000 L
1F
b111 K
b110 E
b101 M
1G
1(
#1480
0(
#1485
b11 I
1F
b111 K
b111 E
b110 -
b110 M
1G
1(
#1490
0(
#1495
b11 C
b111 -
b111 M
0G
1(
#1500
0(
#1505
1#
b1 D
b111 M
1(
#1510
0(
#1515
b10 D
1,
b111 M
1(
#1520
0(
#1525
b11 D
b111 M
1(
#1530
0(
#1535
b100 D
b111 M
1(
#1540
0(
#1545
b101 D
b111 M
1(
#1550
0(
#1555
b110 D
b111 M
b10 P
b10 2
1(
#1560
0(
#1565
1F
b111 K
b10000100 5
b111 D
b10000100 A
b111 M
1+
b10 *
b10 4
1(
#1570
0(
#1575
b1000 D
1H
b111 M
b0 *
b0 4
0+
1(
#1580
0(
#1585
b1001 D
b111 M
1H
1(
#1590
0(
#1595
b1010 D
b111 M
1H
1(
#1600
0(
#1605
b1011 D
b111 M
1H
1(
#1610
0(
#1615
b1100 D
b111 M
1H
1(
#1620
0(
#1625
b1101 D
b111 M
1H
1(
#1630
0(
#1635
b1110 D
b111 M
1H
1(
#1640
0(
#1645
b1111 D
b111 M
1H
1(
#1650
0(
#1655
b10000 D
b111 M
1H
1(
#1660
0(
#1665
b10001 D
b111 M
1H
1(
#1670
0(
#1675
b10010 D
b111 M
1H
1(
#1680
0(
#1685
b10011 D
b111 M
1H
1(
#1690
0(
#1695
b0 I
16
b10100 D
b111 M
1H
1(
#1700
0(
#1705
0F
b0 K
b100 5
0#
06
b10101 D
b0 C
b100 A
b111 M
1H
1(
#1710
0(
#1715
b10 I
1F
b10 K
b11111111111111111111111111111111 L
b0 J
0!
1"
b0 D
0,
b111 M
1H
1(
#1720
0(
#1725
b10 C
b10 J
b111 M
1H
1(
#1730
0(
#1735
b11111111111111111111111111111111 L
1F
b10 K
b110 E
b111 M
1H
1(
#1740
0(
#1745
b11111111111111111111111111111111 L
1F
b10 K
b101 E
b110 -
b110 M
1H
1(
#1750
0(
#1755
b11111111111111111111111111111111 L
1F
b10 K
b100 E
b101 -
b101 M
1H
1(
#1760
0(
#1765
b11111111111111111111111111111111 L
1F
b10 K
b11 E
b100 -
b100 M
1H
1(
#1770
0(
#1775
b11 I
1F
b10 K
b10 E
b11 -
b11 M
1H
1(
#1780
0(
#1785
b11 C
b10 -
b10 M
0H
1(
#1790
0(
#1795
b1 D
1#
b10 M
1(
#1800
0(
#1805
b10 D
1,
b10 M
1(
#1810
0(
#1815
b11 D
b10 M
0O
b1 N
b1 1
1(
#1820
0(
#1825
1F
b10 K
b110 5
b100 D
b10 B
b10 M
1)
b1 '
b1 3
1(
#1830
0(
#1835
b101 D
1H
b10 M
1(
#1840
0(
#1845
b110 D
b10 M
1H
0)
1(
#1850
0(
#1855
b111 D
b10 M
1H
1(
#1860
0(
#1865
b1000 D
b10 M
1H
1(
#1870
0(
#1875
b1001 D
b10 M
1H
1(
#1880
0(
#1885
b1010 D
b10 M
1H
1(
#1890
0(
#1895
b1011 D
b10 M
1H
b110 N
b110 1
1(
#1900
0(
#1905
1F
b10 K
b1000110 5
b1100 D
b1000010 B
b10 M
1H
1)
b110 '
b110 3
1(
#1910
0(
#1915
b1101 D
1G
b10 M
1H
1(
#1920
0(
#1925
b1110 D
b10 M
1H
1G
0)
1(
#1930
0(
#1935
b1111 D
b10 M
1H
1G
1(
#1940
0(
#1945
b10000 D
b10 M
1H
1G
1(
#1950
0(
#1955
b10001 D
b10 M
1H
1G
1(
#1960
0(
#1965
b10010 D
b10 M
1H
1G
1(
#1970
0(
#1975
b10011 D
b10 M
1H
1G
1(
#1980
0(
#1985
b0 I
16
b10100 D
b10 M
1H
1G
1(
#1990
0(
#1995
b11111111111111111111111111111111 L
1F
b1 K
b1000010 5
b0 A
b0 C
06
b10101 D
0#
b10 M
1H
1G
1(
#2000
0(
#2005
b1000 L
1F
b110 K
b10 I
b0 D
0"
1!
b1 J
0,
b10 M
1H
1G
1(
#2010
0(
#2015
b110 J
b10 C
b10 M
1H
1G
1(
#2020
0(
#2025
b10 M
1H
1G
1(
#2030
0(
#2035
b10 M
1H
1G
1(
#2040
0(
#2045
b10 M
1H
1G
1(
#2050
0(
#2055
b10 M
1H
1G
1(
#2060
0(
#2065
b10 M
1H
1G
1(
#2070
0(
#2075
b10 M
1H
1G
1(
#2080
0(
#2085
b10 M
1H
1G
1(
#2090
0(
#2095
b10 M
1H
1G
1(
#2100
0(
#2105
b10 M
1H
1G
1(
#2110
0(
#2115
b10 M
1H
1G
1(
#2120
0(
#2125
b10 M
1H
1G
1(
#2130
0(
#2135
b10 M
1H
1G
1(
#2140
0(
#2145
b10 M
1H
1G
1(
#2150
0(
#2155
b10 M
1H
1G
1(
#2160
0(
#2165
b10 M
1H
1G
1(
#2170
0(
#2175
b10 M
1H
1G
1O
b11 N
b11 1
1(
#2180
0(
#2185
b1000 L
1F
b11 K
b1001010 5
b1001010 B
b10 M
1H
1G
10
b11 '
b11 3
1(
#2190
0(
#2195
b11 J
b10 M
1H
1G
1(
#2200
0(
#2205
b10 M
1H
1G
00
1(
#2210
0(
#2215
b10 M
1H
1G
1(
#2220
0(
#2225
b10 M
1H
1G
1(
#2230
0(
#2235
b10 M
1H
1G
1(
#2240
0(
#2245
b10 M
1H
1G
1(
#2250
0(
#2255
b10 M
1H
1G
1(
#2260
0(
#2265
b10 M
1H
1G
1(
#2270
0(
#2275
b10 M
1H
1G
1(
#2280
0(
#2285
b10 M
1H
1G
1(
#2290
0(
#2295
b10 M
1H
1G
1(
#2300
0(
#2305
b10 M
1H
1G
1(
#2310
0(
#2315
b10 M
1H
1G
1(
#2320
0(
#2325
b10 M
1H
1G
1(
#2330
0(
#2335
b10 M
1H
1G
1(
#2340
0(
#2345
b10 M
1H
1G
b11 P
b11 2
1(
#2350
0(
#2355
b1000 A
b10 M
1H
1G
1+
b11 *
b11 4
1(
#2360
0(
#2365
b10 M
1H
1G
b0 *
b0 4
0+
1(
#2370
0(
#2375
b10 M
1H
1G
1(
#2380
0(
#2385
b10 M
1H
1G
1(
#2390
0(
#2395
b10 M
1H
1G
1(
#2400
0(
#2405
b10 M
1H
1G
1(
#2410
0(
#2415
b10 M
1H
1G
1(
#2420
0(
#2425
b10 M
1H
1G
1(
#2430
0(
#2435
b10 M
1H
1G
1(
#2440
0(
#2445
b10 M
1H
1G
1(
#2450
0(
#2455
b10 M
1H
1G
1(
#2460
0(
#2465
b10 M
1H
1G
1(
#2470
0(
#2475
b10 M
1H
1G
1(
#2480
0(
#2485
b10 M
1H
1G
1(
#2490
0(
#2495
b10 M
1H
1G
1(
#2500
0(
#2505
b10 M
1H
1G
1(
#2510
0(
#2515
b10 M
1H
1G
1(
#2520
0(
#2525
b10 M
1H
1G
1(
#2530
0(
#2535
b10 M
1H
1G
1(
#2540
0(
#2545
b10 M
1H
1G
1(
#2550
0(
#2555
b10 M
1H
1G
b10 P
b10 2
1(
#2560
0(
#2565
1F
b10 K
b1001110 5
b1100 A
b10 M
1H
1G
1+
b10 *
b10 4
1(
#2570
0(
#2575
b11 I
b10 J
b10 M
1H
1G
b0 *
b0 4
0+
1(
#2580
0(
#2585
b11 C
b10 M
1H
1G
1(
#2590
0(
#2595
b1 D
1#
b10 M
1H
1G
1(
#2600
0(
#2605
b10 D
1,
b10 M
1H
1G
1(
#2610
0(
#2615
b11 D
b10 M
1H
1G
1(
#2620
0(
#2625
b100 D
b10 M
1H
1G
1(
#2630
0(
#2635
b101 D
b10 M
1H
1G
b1 P
b1 2
1(
#2640
0(
#2645
b110 D
b1110 A
b10 M
1H
1G
1+
b1 *
b1 4
1(
#2650
0(
#2655
b111 D
b10 M
1H
1G
b0 *
b0 4
0+
1(
#2660
0(
#2665
b1000 D
b10 M
1H
1G
1(
#2670
0(
#2675
b1001 D
b10 M
1H
1G
1(
#2680
0(
#2685
b1010 D
b10 M
1H
1G
1(
#2690
0(
#2695
b1011 D
b10 M
1H
1G
1(
#2700
0(
#2705
b1100 D
b10 M
1H
1G
1(
#2710
0(
#2715
b1101 D
b10 M
1H
1G
1(
#2720
0(
#2725
b1110 D
b10 M
1H
1G
1(
#2730
0(
#2735
b1111 D
b10 M
1H
1G
1(
#2740
0(
#2745
b10000 D
b10 M
1H
1G
b100 P
b100 2
1(
#2750
0(
#2755
1F
b10 K
b1011110 5
b11110 A
b10001 D
b10 M
1H
1G
1+
b100 *
b100 4
1(
#2760
0(
#2765
b10010 D
b10 M
1H
1G
b0 *
b0 4
0+
1(
#2770
0(
#2775
b10011 D
b10 M
1H
1G
1(
#2780
0(
#2785
b0 I
16
b10100 D
b10 M
1H
1G
1(
#2790
0(
#2795
b1000 L
1F
b11 K
b1011010 5
b11010 A
b0 C
06
b10101 D
0#
b10 M
1H
1G
1(
#2800
0(
#2805
b1 I
b0 D
b11 J
0,
b10 M
1H
1G
1(
#2810
0(
#2815
b1 C
b10 M
1H
1G
1(
#2820
0(
#2825
b11 I
1F
b11 K
b11 E
b10 M
1H
1G
1(
#2830
0(
#2835
b11 C
b11 -
b11 M
1H
1G
1(
#2840
0(
#2845
1#
b1 D
b11 M
1H
1G
1(
#2850
0(
#2855
b10 D
1,
b11 M
1H
1G
1(
#2860
0(
#2865
b11 D
b11 M
1H
1G
1(
#2870
0(
#2875
b100 D
b11 M
1H
1G
1/
1(
#2880
0(
#2885
b101 D
b11 M
1H
1G
0/
1(
#2890
0(
#2895
b110 D
b11 M
1H
1G
1(
#2900
0(
#2905
b111 D
b11 M
1H
1G
1(
#2910
0(
#2915
b1000 D
b11 M
1H
1G
1(
#2920
0(
#2925
b1001 D
b11 M
1H
1G
1(
#2930
0(
#2935
b1010 D
b11 M
1H
1G
1(
#2940
0(
