Elevator_controller.v

module controller (
    input [2:0] floor_req,
    input stop,
    input clk,
    input rst,
    output reg door_status

);
//total floor
    parameter MAX = 4;      //0,1,2,3
// states 
    parameter  IDLE = 2'b00, go_up = 2'b01, go_down = 2'b10;

    reg [1:0] current_state;
    reg [1:0] next_state;
    reg [2:0] floor_count;
    reg door;



// state update at every clk pulse
    always @(posedge clk or posedge rst) begin
        if (rst) begin
            current_state <= IDLE;
        end
        else begin
            current_state <= next_state;
        end
    end


// state transitions
    always @(*) begin
        next_state = current_state;
        case (current_state)
        IDLE : begin                                    //In this state lift is not running 
            if ( floor_count < floor_req )begin
                next_state = go_up;
            end
            else if ( floor_count > floor_req ) begin
                next_state = go_down;
            end
        end  

        go_up:begin
            if (stop || floor_count >= floor_req)
                next_state = IDLE;
        
        end   

        go_down : begin
            if (stop || floor_count <= floor_req)
                next_state = IDLE;
        end

        endcase
    end


// floor updation


always @(posedge clk or posedge rst) begin
    if (rst)begin 
        floor_count <= 0;
    end
   
    else if (current_state == go_up) begin
        if (floor_count < floor_req && floor_count < MAX-1)   // ← protection
            floor_count <= floor_count + 1;
    end
    else if (current_state == go_down) begin
        if (floor_count > floor_req && floor_count > 0)             // ← protection
            floor_count <= floor_count - 1;
    end
    // else: hold current floor (implicit)
end
    
    

//output logic
    always @(posedge clk or posedge rst) begin
        if(rst)begin
            door_status <= 0;
        end
        else if(current_state == IDLE && floor_count == floor_req)begin
            door_status <= 1;
        end
        else begin
            door_status <= 0;   
        end
        
    end




endmodule

module controller_tb;
    reg [2:0] floor_req;
    reg stop;
    reg clk;
    reg rst;
    wire door_status;

    controller dut(.floor_req(floor_req), .stop(stop), .clk(clk), .rst(rst), .door_status(door_status));

    initial clk=0;
    always #5 clk = ~clk;

    task floor_input( input [2:0] f);
        begin
            floor_req=f;
            @(posedge clk);
        end 
    endtask

    task stop_input;
    begin
        stop=1;
        @(posedge clk);
        stop=0;
        @(posedge clk);
    end 
    endtask
//----------------------test inputs----------------------

     initial begin
        rst=1;
        stop=0;
        floor_req=0;

        repeat(2)@(posedge clk);
        rst=0;


        // Example test sequence
        floor_input(3'd2);
        repeat(30) @(posedge clk);
        floor_input(3'd0);
        repeat(40) @(posedge clk);
        floor_input(3'd3);
        repeat(50) @(posedge clk);
        $finish;



     end

    initial begin
    $dumpfile("controller.vcd");   // waveform file
    $dumpvars(0, controller_tb);   // dump all signals
    end

    initial begin
        $monitor("T=%0t  | door status=%b ",$time,door_status);
    end
    

    
endmodule

controller.vcd
$date
	Tue Mar 10 18:04:14 2026
$end
$version
	Icarus Verilog
$end
$timescale
	1s
$end
$scope module controller_tb $end
$var wire 1 ! door_status $end
$var reg 1 " clk $end
$var reg 3 # floor_req [2:0] $end
$var reg 1 $ rst $end
$var reg 1 % stop $end
$scope module dut $end
$var wire 1 " clk $end
$var wire 3 & floor_req [2:0] $end
$var wire 1 $ rst $end
$var wire 1 % stop $end
$var parameter 2 ' IDLE $end
$var parameter 32 ( MAX $end
$var parameter 2 ) go_down $end
$var parameter 2 * go_up $end
$var reg 2 + current_state [1:0] $end
$var reg 1 ! door_status $end
$var reg 3 , floor_count [2:0] $end
$var reg 2 - next_state [1:0] $end
$upscope $end
$scope task floor_input $end
$var reg 3 . f [2:0] $end
$upscope $end
$scope task stop_input $end
$upscope $end
$upscope $end
$enddefinitions $end
$comment Show the parameter values. $end
$dumpall
b1 *
b10 )
b100 (
b0 '
$end
#0
$dumpvars
bx .
b0 -
b0 ,
b0 +
b0 &
0%
1$
b0 #
0"
0!
$end
#5
1"
#10
0"
#15
b1 -
b10 #
b10 &
b10 .
0$
1"
#20
0"
#25
b1 +
1"
#30
0"
#35
b1 ,
1"
#40
0"
#45
b0 -
b10 ,
1"
#50
0"
#55
b0 +
1"
#60
0"
#65
1!
1"
#70
0"
#75
1"
#80
0"
#85
1"
#90
0"
#95
1"
#100
0"
#105
1"
#110
0"
#115
1"
#120
0"
#125
1"
#130
0"
#135
1"
#140
0"
#145
1"
#150
0"
#155
1"
#160
0"
#165
1"
#170
0"
#175
1"
#180
0"
#185
1"
#190
0"
#195
1"
#200
0"
#205
1"
#210
0"
#215
1"
#220
0"
#225
1"
#230
0"
#235
1"
#240
0"
#245
1"
#250
0"
#255
1"
#260
0"
#265
1"
#270
0"
#275
1"
#280
0"
#285
1"
#290
0"
#295
1"
#300
0"
#305
1"
#310
0"
#315
1"
#320
0"
#325
0!
b10 -
b0 #
b0 &
b0 .
1"
#330
0"
#335
b10 +
1"
#340
0"
#345
b1 ,
1"
#350
0"
#355
b0 -
b0 ,
1"
#360
0"
#365
b0 +
1"
#370
0"
#375
1!
1"
