Single Elevator/Elevator_dispatcher.v
`timescale 1ns/1ns

module elevator_dispatcher (
    input clk,
    input rst,
    
    // Hall Call Inputs (from outside buttons)
    input call_button_pressed,
    input [2:0] call_floor,
    input upward,          // 1 = UP call, 0 = DOWN call
    input downward,
    
    // Status from all 3 Elevators
    input [2:0] current_floor_E1,
    input [2:0] current_floor_E2,
    input [2:0] current_floor_E3,
    
    input [1:0] direction_E1,   // 00=IDLE, 01=UP, 10=DOWN
    input [1:0] direction_E2,
    input [1:0] direction_E3,
    
    // Assigned Calls to Each Elevator 
    output reg [2:0] assigned_floor_E1,
    output reg       assigned_dir_E1,   // 1=UP, 0=DOWN
    output reg       assign_valid_E1,
    
    output reg [2:0] assigned_floor_E2,
    output reg       assigned_dir_E2,
    output reg       assign_valid_E2,
    
    output reg [2:0] assigned_floor_E3,
    output reg       assigned_dir_E3,
    output reg       assign_valid_E3
);

    reg [3:0] cost_E1, cost_E2, cost_E3;
    reg [1:0] selected_elev;

    // ====================== COST CALCULATION ======================
    always @(*) begin
        // Default high cost
        cost_E1 = 8;
        cost_E2 = 8;
        cost_E3 = 8;

        // Cost for Elevator 1
        if (direction_E1 == 2'b01 && upward)      // Same direction UP
            cost_E1 = (current_floor_E1 > call_floor) ? 15 : (call_floor - current_floor_E1);
        else if (direction_E1 == 2'b10 && downward) // Same direction DOWN
            cost_E1 = (current_floor_E1 < call_floor) ? 15 : (current_floor_E1 - call_floor);
        else
            cost_E1 = 4 + (call_floor > current_floor_E1 ? 
                      (call_floor - current_floor_E1) : (current_floor_E1 - call_floor));

        // Cost for Elevator 2
        if (direction_E2 == 2'b01 && upward)
            cost_E2 = (current_floor_E2 > call_floor) ? 15 : (call_floor - current_floor_E2);
        else if (direction_E2 == 2'b10 && downward)
            cost_E2 = (current_floor_E2 < call_floor) ? 15 : (current_floor_E2 - call_floor);
        else
            cost_E2 = 4 + (call_floor > current_floor_E2 ? 
                      (call_floor - current_floor_E2) : (current_floor_E2 - call_floor));

        // Cost for Elevator 3
        if (direction_E3 == 2'b01 && upward)
            cost_E3 = (current_floor_E3 > call_floor) ? 15 : (call_floor - current_floor_E3);
        else if (direction_E3 == 2'b10 && downward)
            cost_E3 = (current_floor_E3 < call_floor) ? 15 : (current_floor_E3 - call_floor);
        else
            cost_E3 = 4 + (call_floor > current_floor_E3 ? 
                      (call_floor - current_floor_E3) : (current_floor_E3 - call_floor));
    end

    // ====================== ASSIGNMENT LOGIC ======================
    always @(posedge clk or posedge rst) begin
        if (rst) begin
            assigned_floor_E1 <= 0; assign_valid_E1 <= 0;
            assigned_floor_E2 <= 0; assign_valid_E2 <= 0;
            assigned_floor_E3 <= 0; assign_valid_E3 <= 0;
            selected_elev <= 0;
        end
        else if (call_button_pressed) begin
            // Find elevator with minimum cost
            if (cost_E1 <= cost_E2 && cost_E1 <= cost_E3)
                selected_elev <= 2'b01;   // Elevator 1
            else if (cost_E2 <= cost_E3)
                selected_elev <= 2'b10;   // Elevator 2
            else
                selected_elev <= 2'b11;   // Elevator 3

            case (selected_elev)
                2'b01: begin
                    assigned_floor_E1 <= call_floor;
                    assigned_dir_E1   <= (current_floor_E1 <= call_floor) ? 1'b1 : 1'b0;
                    assign_valid_E1   <= 1;
                end
                2'b10: begin
                    assigned_floor_E2 <= call_floor;
                    assigned_dir_E2   <= (current_floor_E2 <= call_floor) ? 1'b1 : 1'b0;
                    assign_valid_E2   <= 1;
                end
                2'b11: begin
                    assigned_floor_E3 <= call_floor;
                    assigned_dir_E3   <= (current_floor_E3 <= call_floor) ? 1'b1 : 1'b0;
                    assign_valid_E3   <= 1;
                end
            endcase
        end
        else begin
            // Clear valid after one cycle 
            assign_valid_E1 <= 0;
            assign_valid_E2 <= 0;
            assign_valid_E3 <= 0;
        end
    end

endmodule

Single Elevator/Elevator2.v
`timescale 1ns/1ns
module controller (
    input new_floor_button_pressed,
    input [2:0] floor_req,
    input call_button_pressed,
    input [2:0] call_floor,
    input stop,
    input clk,
    input rst,
    input  upward,
    input  downward,
    output reg door_status,
    output reg moving_up,
    output reg [2:0] floor_count,
    output [2:0] current_floor,     
    output reg [1:0] direction,          
    output reg moving_down
);

//============= TOTAL FLOORS ====================
    parameter   MAX_FLOOR = 7,
                TIMEOUT_AT=20;

//============= PARAMETER =======================
    parameter   IDLE = 2'b00, 
                GO_UP = 2'b01,
                GO_DOWN = 2'b10,
                OPEN_DOOR = 2'b11;

//============= REGISTERS ======================

    reg [MAX_FLOOR:0] call_request;   // outside
    reg [MAX_FLOOR:0] cabin_request;  // inside  // one bit per floor  -request[2]=1 means'someone requested 2nd floor'
    reg [1:0] current_state;
    reg [1:0] next_state;
    reg [2:0] next_target;
    reg [4:0] door_timing_counter;
    reg has_request_above, has_request_below;
    integer j;
    wire [MAX_FLOOR:0] request = call_request | cabin_request;

    assign current_floor = floor_count;

// Direction output
    always @(*) begin
        if (moving_up)    direction = 2'b01;
        else if (moving_down) direction = 2'b10;
        else              direction = 2'b00;
    end

//      QUEUE FOR FLOOR REQUESTS

always @(posedge clk or posedge rst) begin
    if (rst) begin
        call_request  <= 0;
        cabin_request <= 0;
    end 
    else begin
        if (call_button_pressed) begin
            call_request[call_floor] <= 1'b1;
        end
        if (new_floor_button_pressed) begin
            cabin_request[floor_req] <= 1'b1;
        end
        if (current_state == OPEN_DOOR && timeout) begin
            cabin_request[floor_count] <= 1'b0;
            call_request[floor_count]  <= 1'b0;
        end
    end
end

//    MOVEMENT OF LIFT - UP/DOWN 

reg [2:0]target;
reg found;
integer i;
always @(*) begin
        target = 0;
        found = 0;
        if (request[floor_count]) begin      // if user entered same floor on which lift is present.
            target = floor_count;
            found = 1;
        end
        else if (moving_up) begin
            for (i = floor_count+1 ; i <= MAX_FLOOR; i = i + 1) begin
                if (request[i] && !found) begin
                    target = i;
                    found = 1;
                end
            end
        end 
        else if(moving_down) begin
            for (i = floor_count-1; i >= 0; i = i - 1) begin
                if (request[i] && !found) begin
                    target = i;
                    found = 1;
                end
            end
        end
        else begin               // if lift is not moving in either of the direction
            for(i = 0; i<MAX_FLOOR+1 ; i=i+1)begin                    //boundation - good for single request,for multiple request it should look 
                if (request[i] && !found) begin             //for the nearest floor wrt current floor.
                    target=i;
                    found=1;
                end
            end
        end
    
end

always @(posedge clk or posedge rst) begin
    if(rst)
        next_target <= 0;
    else 
        next_target<=target;
end

//      STATE DECISION

    always @(*) begin
        next_state = current_state;

        case (current_state)

        IDLE: begin
            if (|request) begin
                if (next_target > floor_count)
                    next_state = GO_UP;
                else if (next_target < floor_count)
                    next_state = GO_DOWN;
                else
                    next_state = IDLE;
            end
        end
           
        GO_UP,GO_DOWN:begin
            if (stop || next_target==floor_count ) begin
                next_state=OPEN_DOOR;
            end
            else  begin
                next_state=current_state;
            end
        end   

        OPEN_DOOR : begin
            if (timeout) begin
                next_state=IDLE;
            end
        end
        default: next_state=IDLE;
        endcase
    end

always @(posedge clk or posedge rst) begin
    if (rst) begin
        moving_up<= 1;
        moving_down <=0;
    end 
    else begin

        has_request_above = 1'b0;
        has_request_below = 1'b0;
        // Check ABOVE
        for (j = floor_count + 1; j <= MAX_FLOOR; j = j + 1) begin
            if (request[j]) begin
                has_request_above = 1'b1;
            end
        end
        // Check BELOW
        for (j = 0; j < floor_count; j = j + 1) begin
            if (request[j]) begin
                has_request_below = 1'b1;
            end
        end
        // Direction decision (NO dependency on previous state)
        if (current_state==IDLE || current_state==GO_DOWN || current_state==GO_UP) begin
            if (has_request_above) begin
                moving_up <= 1;
                moving_down <= 0;
            end 
            else if (has_request_below) begin
                moving_down <= 1;
                moving_up <= 0;
            end
        end
        
        // else: no change
    end
end

//      STATE TRANSITIONS

    always @(posedge clk or posedge rst) begin
        if (rst) begin
            current_state <= IDLE;
        end
        else begin
            current_state <= next_state;
        end
    end

//      FLOOR TRANSITION

always @(posedge clk or posedge rst) begin
    if (rst)begin 
        floor_count <= 0;
    end
    else if (current_state == GO_UP) begin
        if (floor_count < next_target && floor_count < MAX_FLOOR)   //  protection
                floor_count <= floor_count + 1;
        end
    else if (current_state == GO_DOWN) begin
        if (floor_count > next_target && floor_count > 0)             //  protection
            floor_count <= floor_count - 1;
        end
end

//              COUNTER

always @(posedge clk or posedge rst) begin
    if (rst)begin
        door_timing_counter <= 0;
    end
    else if (current_state == OPEN_DOOR) begin
        if(door_timing_counter <= TIMEOUT_AT)
            door_timing_counter <= door_timing_counter+1;
    end
    else
        door_timing_counter <= 0;
end

    wire timeout=(door_timing_counter==TIMEOUT_AT);

//       OUTPUT LOGIC

    always @(posedge clk or posedge rst) begin
        if (rst) begin
            door_status <= 1'b0;
        end
        else if(current_state == OPEN_DOOR && !timeout)begin
            door_status <= 1'b1;
        end
        else begin
            door_status <= 1'b0; 
        end
        
    end

endmodule

Single Elevator/Elevator_grp.v
`timescale 1ns/1ns


module multi_elevator_top (
    input clk,
    input rst,

    input [2:0]   floor_req,                   
    input         new_floor_button_pressed,     
    input [2:0]   call_floor,                   
    input         call_button_pressed,          
    input         upward,                       
    input         downward,                     
    input         stop, 
    // input [2:0]   current_floorE1,
    // input [2:0]   current_floorE2,
    // input [2:0]   current_floorE3, 

    // input [1:0]   direction
    // input [1:0]   direction
    // input [1:0]   direction

    // Elevator 1
    output wire       door_statusE1,
    output wire       moving_upE1,
    output wire       moving_downE1,
    // output wire [2:0] current_floorE1,

    // Elevator 2
    output wire       door_statusE2,
    output wire       moving_upE2,
    output wire       moving_downE2,
    // output wire [2:0] current_floorE2,

    // Elevator 3
    output wire       door_statusE3,
    output wire       moving_upE3,
    output wire       moving_downE3
    // output wire [2:0] current_floorE3
);


    // Internal wires for communication with Dispatcher
    // Status from Elevators to Dispatcher

    wire [1:0] direction_E1, direction_E2, direction_E3;

    // Assigned calls from Dispatcher to each Elevator
    wire [2:0] assigned_floor_E1, assigned_floor_E2, assigned_floor_E3;
    wire       assigned_dir_E1,   assigned_dir_E2,   assigned_dir_E3;  // 1=UP, 0=DOWN
    wire       assign_valid_E1,   assign_valid_E2,   assign_valid_E3;


    // Instantiate 3 Independent Elevators

    controller ELEV1 (
        .clk(clk),
        .rst(rst),
        .floor_req(floor_req),
        .new_floor_button_pressed(new_floor_button_pressed),
        .call_floor(assigned_floor_E1),      
        .upward(assigned_dir_E1 & assign_valid_E1),
        .downward(~assigned_dir_E1 & assign_valid_E1),
        .stop(stop),
        .door_status(door_statusE1),
        .moving_up(moving_upE1),
        .moving_down(moving_downE1),
        .current_floor(current_floorE1),        // Status to dispatcher
        .direction(direction_E1)            // Status to dispatcher
    );

    controller ELEV2 (
        .clk(clk),
        .rst(rst),
        .floor_req(floor_req),
        .new_floor_button_pressed(new_floor_button_pressed),
        .call_floor(assigned_floor_E2),
        .upward(assigned_dir_E2 & assign_valid_E2),
        .downward(~assigned_dir_E2 & assign_valid_E2),
        .stop(stop),
        .door_status(door_statusE2),
        .moving_up(moving_upE2),
        .moving_down(moving_downE2),
        .current_floor(current_floorE2),
        .direction(direction_E2)
    );

    controller ELEV3 (
        .clk(clk),
        .rst(rst),
        .floor_req(floor_req),
        .new_floor_button_pressed(new_floor_button_pressed),
        .call_floor(assigned_floor_E3),
        .upward(assigned_dir_E3 & assign_valid_E3),
        .downward(~assigned_dir_E3 & assign_valid_E3),
        .stop(stop),
        .door_status(door_statusE3),
        .moving_up(moving_upE3),
        .moving_down(moving_downE3),
        .current_floor(current_floorE3),
        .direction(direction_E3)
    );

    // ===================================================================
    // Instantiate Central Dispatcher
    // ===================================================================

    elevator_dispatcher GROUP_CTRL (
        .clk(clk),
        .rst(rst),

        // Hall Call Inputs
        .call_button_pressed (call_button_pressed),
        .call_floor(call_floor),
        .upward(upward),
        .downward(downward),

        // Status from all Elevators
        .current_floor_E1(current_floorE1),
        .current_floor_E2(current_floorE2),
        .current_floor_E3(current_floorE3),

        .direction_E1(direction_E1),
        .direction_E2(direction_E2),
        .direction_E3(direction_E3),

        // Assigned Calls to Elevators
        .assigned_floor_E1(assigned_floor_E1),
        .assigned_dir_E1(assigned_dir_E1),
        .assign_valid_E1(assign_valid_E1),

        .assigned_floor_E2(assigned_floor_E2),
        .assigned_dir_E2(assigned_dir_E2),
        .assign_valid_E2(assign_valid_E2),

        .assigned_floor_E3(assigned_floor_E3),
        .assigned_dir_E3(assigned_dir_E3),
        .assign_valid_E3(assign_valid_E3)
    );

endmodule

Single Elevator/Elevator_tb.v
`timescale 1ns/1ns

module multi_elevator_tb;

    // ==================== Signals ====================
    reg clk;
    reg rst;

    // Inputs to DUT
    reg [2:0]   floor_req;
    reg         new_floor_button_pressed;
    reg [2:0]   call_floor;
    reg         call_button_pressed;
    reg         upward;
    reg         downward;
    reg         stop;

    // Outputs from DUT
    wire        door_statusE1, moving_upE1, moving_downE1;
    wire [2:0]  current_floorE1;

    wire        door_statusE2, moving_upE2, moving_downE2;
    wire [2:0]  current_floorE2;

    wire        door_statusE3, moving_upE3, moving_downE3;
    wire [2:0]  current_floorE3;

    // ==================== Instantiate DUT ====================
    multi_elevator_top DUT (

        .clk(clk),
        .rst(rst),

        .floor_req(floor_req),
        .new_floor_button_pressed(new_floor_button_pressed),
        .call_floor(call_floor),
        .call_button_pressed(call_button_pressed),
        .upward(upward),
        .downward(downward),
        .stop(stop),


        .door_statusE1(door_statusE1),
        .moving_upE1(moving_upE1),
        .moving_downE1(moving_downE1),
        .current_floorE1(current_floorE1),


        .door_statusE2(door_statusE2),
        .moving_upE2(moving_upE2),
        .moving_downE2(moving_downE2),
        .current_floorE2(current_floorE2),


        .door_statusE3(door_statusE3),
        .moving_upE3(moving_upE3),
        .moving_downE3(moving_downE3),
        .current_floorE3(current_floorE3)
    );

    // ==================== Clock Generation ====================
    initial begin
        clk = 0;
        forever #5 clk = ~clk;   // 100 MHz clock (10ns period)
    end

    // ==================== Reset Task ====================
    task reset_system;
        begin
            rst = 1;
            floor_req = 0;
            new_floor_button_pressed = 0;
            call_floor = 0;
            call_button_pressed = 0;
            upward = 0;
            downward = 0;
            stop = 0;
            repeat(10) @(posedge clk);
            rst = 0;
            repeat(5) @(posedge clk);
            $display("[%0t] System Reset Done", $time);
        end
    endtask

    // ==================== Random Hall Call Task ====================
    task random_hall_call;
        integer rand_floor;
        begin
            rand_floor = $urandom_range(0, MAX_FLOOR);           // Random floor 0 to 7
            call_floor = rand_floor;

            // Random direction (70% chance of UP, 30% DOWN for realism)
            if ($random % 10 < 7) begin
                upward = 1; downward = 0;
            end else begin
                upward = 0; downward = 1;
            end

            call_button_pressed = 1;
            @(posedge clk);
            call_button_pressed = 0;     // Pulse for one cycle

            $display("[%0t] Random Hall Call: Floor=%0d, Dir=%s", 
                     $time, rand_floor, upward ? "UP" : "DOWN");
        end
    endtask

    // ==================== Random Cabin Button Press ====================
    task random_cabin_press;
        integer rand_floor;
        begin
            rand_floor = $urandom_range(0, MAX_FLOOR);
            floor_req = rand_floor;
            new_floor_button_pressed = 1;
            @(posedge clk);
            new_floor_button_pressed = 0;

            $display("[%0t] Random Cabin Press: Floor=%0d", $time, rand_floor);
        end
    endtask

    // ==================== Random Emergency Stop ====================
    task random_emergency;
        begin
            stop = 1;
            @(posedge clk);
            stop = 0;
            $display("[%0t] *** EMERGENCY STOP Triggered ***", $time);
        end
    endtask

    // ==================== Monitor Task (Optional) ====================
    always @(posedge clk) begin
        if (door_statusE1 || door_statusE2 || door_statusE3) begin
            $display("[%0t] Door Open - E1:%0d E2:%0d E3:%0d | Floors: %0d %0d %0d", 
                     $time, door_statusE1, door_statusE2, door_statusE3,
                     current_floorE1, current_floorE2, current_floorE3);
        end
    end

    // ==================== Main Test Sequence ====================
    initial begin
        $dumpfile("multi_elevator_tb.vcd");
        $dumpvars(0, multi_elevator_tb);

        reset_system();

        repeat(5) @(posedge clk);

        $display("=== Starting Random Stimulus Test ===");
        repeat(80) begin          
            // Randomly generate hall calls or cabin presses
            if ($random % 5 == 0)      
                random_emergency();
            else if ($random % 3 == 0) 
                random_hall_call();
            else                       
                random_cabin_press();

            // Small random delay between requests
            repeat($urandom_range(5, 25)) @(posedge clk);
        end

        $display("=== Random Test Completed ===");
        repeat(100) @(posedge clk);
        $finish;
    end

endmodule

Single Elevator/multi_elevator_tb.vcd
$date
	Thu Apr 09 10:47:36 2026
$end
$version
	Icarus Verilog
$end
$timescale
	1ns
$end
$scope module multi_elevator_tb $end
$var wire 1 ! moving_upE3 $end
$var wire 1 " moving_upE2 $end
$var wire 1 # moving_upE1 $end
$var wire 1 $ moving_downE3 $end
$var wire 1 % moving_downE2 $end
$var wire 1 & moving_downE1 $end
$var wire 1 ' door_statusE3 $end
$var wire 1 ( door_statusE2 $end
$var wire 1 ) door_statusE1 $end
$var wire 3 * current_floorE3 [2:0] $end
$var wire 3 + current_floorE2 [2:0] $end
$var wire 3 , current_floorE1 [2:0] $end
$var reg 1 - call_button_pressed $end
$var reg 3 . call_floor [2:0] $end
$var reg 1 / clk $end
$var reg 1 0 downward $end
$var reg 3 1 floor_req [2:0] $end
$var reg 1 2 new_floor_button_pressed $end
$var reg 1 3 rst $end
$var reg 1 4 stop $end
$var reg 1 5 upward $end
$scope module DUT $end
$var wire 1 - call_button_pressed $end
$var wire 3 6 call_floor [2:0] $end
$var wire 1 / clk $end
$var wire 1 0 downward $end
$var wire 3 7 floor_req [2:0] $end
$var wire 1 2 new_floor_button_pressed $end
$var wire 1 3 rst $end
$var wire 1 4 stop $end
$var wire 1 5 upward $end
$var wire 1 ! moving_upE3 $end
$var wire 1 " moving_upE2 $end
$var wire 1 # moving_upE1 $end
$var wire 1 $ moving_downE3 $end
$var wire 1 % moving_downE2 $end
$var wire 1 & moving_downE1 $end
$var wire 1 ' door_statusE3 $end
$var wire 1 ( door_statusE2 $end
$var wire 1 ) door_statusE1 $end
$var wire 2 8 direction_E3 [1:0] $end
$var wire 2 9 direction_E2 [1:0] $end
$var wire 2 : direction_E1 [1:0] $end
$var wire 3 ; current_floorE3 [2:0] $end
$var wire 3 < current_floorE2 [2:0] $end
$var wire 3 = current_floorE1 [2:0] $end
$var wire 3 > assigned_floor_E3 [2:0] $end
$var wire 3 ? assigned_floor_E2 [2:0] $end
$var wire 3 @ assigned_floor_E1 [2:0] $end
$var wire 1 A assigned_dir_E3 $end
$var wire 1 B assigned_dir_E2 $end
$var wire 1 C assigned_dir_E1 $end
$var wire 1 D assign_valid_E3 $end
$var wire 1 E assign_valid_E2 $end
$var wire 1 F assign_valid_E1 $end
$scope module ELEV1 $end
$var wire 1 G call_button_pressed $end
$var wire 1 / clk $end
$var wire 3 H current_floor [2:0] $end
$var wire 1 I downward $end
$var wire 3 J floor_req [2:0] $end
$var wire 1 2 new_floor_button_pressed $end
$var wire 8 K request [7:0] $end
$var wire 1 3 rst $end
$var wire 1 4 stop $end
$var wire 1 L upward $end
$var wire 1 M timeout $end
$var wire 3 N call_floor [2:0] $end
$var parameter 2 O GO_DOWN $end
$var parameter 2 P GO_UP $end
$var parameter 2 Q IDLE $end
$var parameter 32 R MAX_FLOOR $end
$var parameter 2 S OPEN_DOOR $end
$var parameter 32 T TIMEOUT_AT $end
$var reg 8 U cabin_request [7:0] $end
$var reg 8 V call_request [7:0] $end
$var reg 2 W current_state [1:0] $end
$var reg 2 X direction [1:0] $end
$var reg 1 ) door_status $end
$var reg 5 Y door_timing_counter [4:0] $end
$var reg 3 Z floor_count [2:0] $end
$var reg 1 [ found $end
$var reg 1 \ has_request_above $end
$var reg 1 ] has_request_below $end
$var reg 1 & moving_down $end
$var reg 1 # moving_up $end
$var reg 2 ^ next_state [1:0] $end
$var reg 3 _ next_target [2:0] $end
$var reg 3 ` target [2:0] $end
$var integer 32 a i [31:0] $end
$var integer 32 b j [31:0] $end
$upscope $end
$scope module ELEV2 $end
$var wire 1 c call_button_pressed $end
$var wire 1 / clk $end
$var wire 3 d current_floor [2:0] $end
$var wire 1 e downward $end
$var wire 3 f floor_req [2:0] $end
$var wire 1 2 new_floor_button_pressed $end
$var wire 8 g request [7:0] $end
$var wire 1 3 rst $end
$var wire 1 4 stop $end
$var wire 1 h upward $end
$var wire 1 i timeout $end
$var wire 3 j call_floor [2:0] $end
$var parameter 2 k GO_DOWN $end
$var parameter 2 l GO_UP $end
$var parameter 2 m IDLE $end
$var parameter 32 n MAX_FLOOR $end
$var parameter 2 o OPEN_DOOR $end
$var parameter 32 p TIMEOUT_AT $end
$var reg 8 q cabin_request [7:0] $end
$var reg 8 r call_request [7:0] $end
$var reg 2 s current_state [1:0] $end
$var reg 2 t direction [1:0] $end
$var reg 1 ( door_status $end
$var reg 5 u door_timing_counter [4:0] $end
$var reg 3 v floor_count [2:0] $end
$var reg 1 w found $end
$var reg 1 x has_request_above $end
$var reg 1 y has_request_below $end
$var reg 1 % moving_down $end
$var reg 1 " moving_up $end
$var reg 2 z next_state [1:0] $end
$var reg 3 { next_target [2:0] $end
$var reg 3 | target [2:0] $end
$var integer 32 } i [31:0] $end
$var integer 32 ~ j [31:0] $end
$upscope $end
$scope module ELEV3 $end
$var wire 1 !" call_button_pressed $end
$var wire 1 / clk $end
$var wire 3 "" current_floor [2:0] $end
$var wire 1 #" downward $end
$var wire 3 $" floor_req [2:0] $end
$var wire 1 2 new_floor_button_pressed $end
$var wire 8 %" request [7:0] $end
$var wire 1 3 rst $end
$var wire 1 4 stop $end
$var wire 1 &" upward $end
$var wire 1 '" timeout $end
$var wire 3 (" call_floor [2:0] $end
$var parameter 2 )" GO_DOWN $end
$var parameter 2 *" GO_UP $end
$var parameter 2 +" IDLE $end
$var parameter 32 ," MAX_FLOOR $end
$var parameter 2 -" OPEN_DOOR $end
$var parameter 32 ." TIMEOUT_AT $end
$var reg 8 /" cabin_request [7:0] $end
$var reg 8 0" call_request [7:0] $end
$var reg 2 1" current_state [1:0] $end
$var reg 2 2" direction [1:0] $end
$var reg 1 ' door_status $end
$var reg 5 3" door_timing_counter [4:0] $end
$var reg 3 4" floor_count [2:0] $end
$var reg 1 5" found $end
$var reg 1 6" has_request_above $end
$var reg 1 7" has_request_below $end
$var reg 1 $ moving_down $end
$var reg 1 ! moving_up $end
$var reg 2 8" next_state [1:0] $end
$var reg 3 9" next_target [2:0] $end
$var reg 3 :" target [2:0] $end
$var integer 32 ;" i [31:0] $end
$var integer 32 <" j [31:0] $end
$upscope $end
$scope module GROUP_CTRL $end
$var wire 1 - call_button_pressed $end
$var wire 3 =" call_floor [2:0] $end
$var wire 1 / clk $end
$var wire 3 >" current_floor_E1 [2:0] $end
$var wire 3 ?" current_floor_E2 [2:0] $end
$var wire 3 @" current_floor_E3 [2:0] $end
$var wire 2 A" direction_E1 [1:0] $end
$var wire 2 B" direction_E2 [1:0] $end
$var wire 2 C" direction_E3 [1:0] $end
$var wire 1 0 downward $end
$var wire 1 3 rst $end
$var wire 1 5 upward $end
$var reg 1 F assign_valid_E1 $end
$var reg 1 E assign_valid_E2 $end
$var reg 1 D assign_valid_E3 $end
$var reg 1 C assigned_dir_E1 $end
$var reg 1 B assigned_dir_E2 $end
$var reg 1 A assigned_dir_E3 $end
$var reg 3 D" assigned_floor_E1 [2:0] $end
$var reg 3 E" assigned_floor_E2 [2:0] $end
$var reg 3 F" assigned_floor_E3 [2:0] $end
$var reg 4 G" cost_E1 [3:0] $end
$var reg 4 H" cost_E2 [3:0] $end
$var reg 4 I" cost_E3 [3:0] $end
$var reg 2 J" selected_elev [1:0] $end
$upscope $end
$upscope $end
$scope task random_cabin_press $end
$var integer 32 K" rand_floor [31:0] $end
$upscope $end
$scope task random_emergency $end
$upscope $end
$scope task random_hall_call $end
$var integer 32 L" rand_floor [31:0] $end
$upscope $end
$scope task reset_system $end
$upscope $end
$upscope $end
$enddefinitions $end
$comment Show the parameter values. $end
$dumpall
b10100 ."
b11 -"
b111 ,"
b0 +"
b1 *"
b10 )"
b10100 p
b11 o
b111 n
b0 m
b1 l
b10 k
b10100 T
b11 S
b111 R
b0 Q
b1 P
b10 O
$end
#0
$dumpvars
bx L"
bx K"
b0 J"
b100 I"
b100 H"
b100 G"
b0 F"
b0 E"
b0 D"
b1 C"
b1 B"
b1 A"
b0 @"
b0 ?"
b0 >"
b0 ="
bx <"
b1000 ;"
b0 :"
b0 9"
b0 8"
x7"
x6"
05"
b0 4"
b0 3"
b1 2"
b0 1"
b0 0"
b0 /"
b0 ("
0'"
0&"
b0 %"
b0 $"
0#"
b0 ""
z!"
bx ~
b1000 }
b0 |
b0 {
b0 z
xy
xx
0w
b0 v
b0 u
b1 t
b0 s
b0 r
b0 q
b0 j
0i
0h
b0 g
b0 f
0e
b0 d
zc
bx b
b1000 a
b0 `
b0 _
b0 ^
x]
x\
0[
b0 Z
b0 Y
b1 X
b0 W
b0 V
b0 U
b0 N
0M
0L
b0 K
b0 J
0I
b0 H
zG
0F
0E
0D
xC
xB
xA
b0 @
b0 ?
b0 >
b0 =
b0 <
b0 ;
b1 :
b1 9
b1 8
b0 7
b0 6
05
04
13
02
b0 1
00
0/
b0 .
0-
b0 ,
b0 +
b0 *
0)
0(
0'
0&
0%
0$
1#
1"
1!
$end
#5
1/
#10
0/
#15
1/
#20
0/
#25
1/
#30
0/
#35
1/
#40
0/
#45
1/
#50
0/
#55
1/
#60
0/
#65
1/
#70
0/
#75
1/
#80
0/
#85
1/
#90
0/
#95
b0 b
0]
0\
b0 ~
0y
0x
b0 <"
07"
06"
03
1/
#100
0/
#105
b0 <"
b0 ~
b0 b
1/
#110
0/
#115
b0 b
b0 ~
b0 <"
1/
#120
0/
#125
b0 <"
b0 ~
b0 b
1/
#130
0/
#135
b0 b
b0 ~
b0 <"
1/
#140
0/
#145
b0 <"
b0 ~
b0 b
1/
#150
0/
#155
b0 b
b0 ~
b0 <"
1/
#160
0/
#165
b0 <"
b0 ~
b0 b
1/
#170
0/
#175
b0 b
b0 ~
b0 <"
1/
#180
0/
#185
b0 <"
b0 ~
b0 b
1/
#190
0/
#195
1[
b100 `
b1000 a
1w
b100 |
b1000 }
15"
b100 :"
b1000 ;"
b10000 K
b10000 g
b10000 %"
b10000 U
b10000 q
b10000 /"
b0 b
b0 ~
b0 <"
12
b100 1
b100 7
b100 J
b100 f
b100 $"
b100 K"
1/
#200
0/
#205
b1 8"
b1 z
b1 ^
b100 9"
b100 {
b100 _
16"
b0 <"
1x
b0 ~
1\
b0 b
02
1/
#210
0/
#215
b1 W
b1 s
b1 1"
b0 b
1\
b0 ~
1x
b0 <"
16"
1/
#220
0/
#225
b1000 ;"
15"
b100 :"
b1000 }
1w
b100 |
b1000 a
1[
b100 `
b101 I"
b101 H"
b101 G"
b1 *
b1 ;
b1 ""
b1 @"
b1 4"
b1 +
b1 <
b1 d
b1 ?"
b1 v
b1 ,
b1 =
b1 H
b1 >"
b1 Z
b0 <"
16"
b0 ~
1x
b0 b
1\
1/
#230
0/
#235
b1000 a
1[
b100 `
b1000 }
1w
b100 |
b1000 ;"
15"
b100 :"
b110 I"
b110 H"
b110 G"
b10 ,
b10 =
b10 H
b10 >"
b10 Z
b10 +
b10 <
b10 d
b10 ?"
b10 v
b10 *
b10 ;
b10 ""
b10 @"
b10 4"
b1 b
1\
b1 ~
1x
b1 <"
16"
1/
#240
0/
#245
b1000 ;"
15"
b100 :"
b1000 }
1w
b100 |
b1000 a
1[
b100 `
b111 I"
b111 H"
b111 G"
b11 *
b11 ;
b11 ""
b11 @"
b11 4"
b11 +
b11 <
b11 d
b11 ?"
b11 v
b11 ,
b11 =
b11 H
b11 >"
b11 Z
b10 <"
16"
b10 ~
1x
b10 b
1\
1/
#250
0/
#255
b11 ^
1[
b100 `
b11 z
1w
b100 |
b11 8"
15"
b100 :"
b1000 I"
b1000 H"
b1000 G"
b100 ,
b100 =
b100 H
b100 >"
b100 Z
b100 +
b100 <
b100 d
b100 ?"
b100 v
b100 *
b100 ;
b100 ""
b100 @"
b100 4"
b11 b
1\
b11 ~
1x
b11 <"
16"
1/
#260
0/
#265
b11 1"
b11 s
b11 W
b100 <"
06"
b100 ~
0x
b100 b
0\
1/
#270
0/
#275
b1 Y
1)
b1 u
1(
b1 3"
1'
b100 b
b100 ~
b100 <"
1/
#280
0/
#285
b10 3"
b10 u
b10 Y
b100 <"
b100 ~
b100 b
1/
#290
0/
#295
b11 Y
b11 u
b11 3"
b100 b
b100 ~
b100 <"
1/
#300
0/
#305
15"
b100 :"
1w
b100 |
1[
b100 `
b10001 %"
b10001 g
b10001 K
b100 3"
b10001 /"
b100 u
b10001 q
b100 Y
b10001 U
b100 <"
b100 ~
b100 b
12
b0 1
b0 7
b0 J
b0 f
b0 $"
b0 K"
1/
#310
0/
#315
b101 Y
b101 u
b101 3"
1]
b100 b
1y
b100 ~
17"
b100 <"
02
1/
#320
0/
#325
b110 3"
b110 u
b110 Y
b100 <"
17"
b100 ~
1y
b100 b
1]
1/
#330
0/
#335
b111 Y
b111 u
b111 3"
b100 b
1]
b100 ~
1y
b100 <"
17"
1/
#340
0/
#345
b1000 3"
b1000 u
b1000 Y
b100 <"
17"
b100 ~
1y
b100 b
1]
1/
#350
0/
#355
b1001 Y
b1001 u
b1001 3"
b100 b
1]
b100 ~
1y
b100 <"
17"
1/
#360
0/
#365
b1010 3"
b1010 u
b1010 Y
b100 <"
17"
b100 ~
1y
b100 b
1]
1/
#370
0/
#375
b1011 Y
b1011 u
b1011 3"
b100 b
1]
b100 ~
1y
b100 <"
17"
1/
#380
0/
#385
b1100 3"
b1100 u
b1100 Y
b100 <"
17"
b100 ~
1y
b100 b
1]
1/
#390
0/
#395
b1101 Y
b1101 u
b1101 3"
b100 b
1]
b100 ~
1y
b100 <"
17"
1/
#400
0/
